netbox_virtual_circuit_plugin/.DS_Store
netbox_virtual_circuit_plugin/__init__.py
netbox_virtual_circuit_plugin/admin.py
netbox_virtual_circuit_plugin/choices.py
netbox_virtual_circuit_plugin/filters.py
netbox_virtual_circuit_plugin/forms.py
netbox_virtual_circuit_plugin/models.py
netbox_virtual_circuit_plugin/navigation.py
netbox_virtual_circuit_plugin/tables.py
netbox_virtual_circuit_plugin/template_content.py
netbox_virtual_circuit_plugin/text1.txt
netbox_virtual_circuit_plugin/text2.txt
netbox_virtual_circuit_plugin/urls.py
netbox_virtual_circuit_plugin/views.py
netbox_virtual_circuit_plugin/api/__init__.py
netbox_virtual_circuit_plugin/api/serializers.py
netbox_virtual_circuit_plugin/api/urls.py
netbox_virtual_circuit_plugin/api/views.py
netbox_virtual_circuit_plugin/migrations/0001_initial.py
netbox_virtual_circuit_plugin/migrations/0002_metadata.py
netbox_virtual_circuit_plugin/migrations/0003_vcid_size.py
netbox_virtual_circuit_plugin/migrations/0004_changelog.py
netbox_virtual_circuit_plugin/migrations/0005_vlan_related_name.py
netbox_virtual_circuit_plugin/migrations/0006_description.py
netbox_virtual_circuit_plugin/migrations/__init__.py
netbox_virtual_circuit_plugin/migrations/__pycache__/0001_initial.cpython-37.pyc
netbox_virtual_circuit_plugin/migrations/__pycache__/0002_metadata.cpython-37.pyc
netbox_virtual_circuit_plugin/migrations/__pycache__/0003_vcid_size.cpython-37.pyc
netbox_virtual_circuit_plugin/migrations/__pycache__/0004_changelog.cpython-37.pyc
netbox_virtual_circuit_plugin/migrations/__pycache__/0005_vlan_related_name.cpython-37.pyc
netbox_virtual_circuit_plugin/migrations/__pycache__/0006_description.cpython-37.pyc
netbox_virtual_circuit_plugin/migrations/__pycache__/__init__.cpython-37.pyc
netbox_virtual_circuit_plugin/templates/netbox_virtual_circuit_plugin/virtual_circuit.html
netbox_virtual_circuit_plugin/templates/netbox_virtual_circuit_plugin/virtual_circuit_edit.html
netbox_virtual_circuit_plugin-2.0.0.dist-info/LICENSE
netbox_virtual_circuit_plugin-2.0.0.dist-info/METADATA
netbox_virtual_circuit_plugin-2.0.0.dist-info/WHEEL
netbox_virtual_circuit_plugin-2.0.0.dist-info/top_level.txt
netbox_virtual_circuit_plugin-2.0.0.dist-info/RECORD
