Metadata-Version: 2.1
Name: netbox-virtual-circuit-plugin
Version: 2.0.0
Summary: A Netbox plugin that supports Virtual Circuit management
Home-page: https://github.com/vapor-ware/netbox-virtual-circuit-plugin
Author: Hoanh An
License: GNU General Public License v3.0
Platform: UNKNOWN
License-File: LICENSE
